cyberintegrations/__init__.py
cyberintegrations/const.py
cyberintegrations/cyberintegrations.py
cyberintegrations/decorators.py
cyberintegrations/exception.py
cyberintegrations/logger.py
cyberintegrations/utils.py
cyberintegrations/adapters/__init__.py
cyberintegrations/adapters/misp_adapter.py
cyberintegrations/adapters/openCTI_adapter.py
cyberintegrations-0.14.1.dist-info/LICENSE
cyberintegrations-0.14.1.dist-info/METADATA
cyberintegrations-0.14.1.dist-info/WHEEL
cyberintegrations-0.14.1.dist-info/top_level.txt
cyberintegrations-0.14.1.dist-info/RECORD
