Metadata-Version: 2.1
Name: cyberintegrations
Version: 0.14.1
Summary: Python library - modules for processing data from the TI and DRP system collected in one library. This library simplifies work with the products API and gives you the flexibility to customize the search and retrieval of data from the system.
Author: Cyberintegrations
Author-email: cyberintegrationsdev@gmail.com
License: MIT
Classifier: Programming Language :: Python :: 3
Classifier: License :: OSI Approved :: MIT License
Classifier: Operating System :: OS Independent
Requires-Python: >=3.7
License-File: LICENSE
Requires-Dist: requests>=2.31.0
Requires-Dist: urllib3>=2.0.2
